output_audio/__init__.py
output_audio-0.3.0.dist-info/LICENSE
output_audio-0.3.0.dist-info/METADATA
output_audio-0.3.0.dist-info/WHEEL
output_audio-0.3.0.dist-info/RECORD
