Metadata-Version: 2.3
Name: output-audio
Version: 0.3.0
Summary: Output audio with playlist.
License: MIT
Author: Allen Chou
Author-email: f1470891079@gmail.com
Requires-Python: >=3.11,<4
Classifier: License :: OSI Approved :: MIT License
Classifier: Programming Language :: Python :: 3
Classifier: Programming Language :: Python :: 3.11
Classifier: Programming Language :: Python :: 3.12
Classifier: Programming Language :: Python :: 3.13
Provides-Extra: all
Requires-Dist: azure-cognitiveservices-speech (>=1.40.0,<2.0.0)
Requires-Dist: google-cloud-texttospeech (>=2.20.0,<3.0.0)
Requires-Dist: google-genai (>=1.16.1,<2.0.0)
Requires-Dist: numpy (>=2,<3)
Requires-Dist: openai (>=1.53,<2.0) ; extra == "all"
Requires-Dist: pydantic (>=2,<3)
Requires-Dist: sounddevice (>=0,<1)
Requires-Dist: str-or-none (>=0.1.0,<1.0.0)
Project-URL: Bug Tracker, https://github.com/allen2c/output-audio/issues
Project-URL: Homepage, https://github.com/allen2c/output-audio
Project-URL: Repository, https://github.com/allen2c/output-audio
